README.md
setup.py
qth_national_rail/__init__.py
qth_national_rail/version.py
qth_national_rail.egg-info/PKG-INFO
qth_national_rail.egg-info/SOURCES.txt
qth_national_rail.egg-info/dependency_links.txt
qth_national_rail.egg-info/entry_points.txt
qth_national_rail.egg-info/requires.txt
qth_national_rail.egg-info/top_level.txt